{"tournament_id": "3103", "built_at": "2026-04-12T17:17:39.836169", "total_cats": 103, "athletes": [{"name": "Prince Raghuraj Tomar Jr", "team": "Logic", "division": "Juvenile Male BLUE Rooster", "category_id": "2815609", "mat": "", "fight_num": "", "fight_time": ""}, {"name": "Tyler James Trinh", "team": "Logic", "division": "Juvenile Male BLUE Light Feather", "category_id": "2815611", "mat": "3", "fight_num": "24", "fight_time": "Sun 04/12 at 04:44 PM"}, {"name": "Seth James Sacchi", "team": "Movement Art", "division": "Juvenile Male BLUE Light Feather", "category_id": "2815611", "mat": "3", "fight_num": "24", "fight_time": "Sun 04/12 at 04:44 PM"}, {"name": "Cristian  Eduardo Salgado", "team": "Caio Terra Academy - Alexandria", "division": "Juvenile Male BLUE Feather", "category_id": "2815613", "mat": "4", "fight_num": "26", "fight_time": "Sun 04/12 at 04:56 PM"}, {"name": "Oscar Marques Cavalcante Bisneto", "team": "Gracie Humaita Ashburn", "division": "Juvenile Male BLUE Feather", "category_id": "2815613", "mat": "4", "fight_num": "26", "fight_time": "Sun 04/12 at 04:56 PM"}, {"name": "Dylan Phuc Tran", "team": "Logic", "division": "Juvenile Male BLUE Light", "category_id": "2815615", "mat": "3", "fight_num": "20", "fight_time": "Sun 04/12 at 04:29 PM"}, {"name": "Talles Felix dos Reis Bispo", "team": "Banana Jiu-Jitsu", "division": "Juvenile Male BLUE Light", "category_id": "2815615", "mat": "3", "fight_num": "20", "fight_time": "Sun 04/12 at 04:29 PM"}, {"name": "Jaden Samuel Landa", "team": "A-Force Brazilian Jiu-Jitsu", "division": "Juvenile Male BLUE Light", "category_id": "2815615", "mat": "3", "fight_num": "19", "fight_time": "Sun 04/12 at 04:24 PM"}, {"name": "Leonardo Reed da Silva", "team": "Essential Jiu-Jitsu", "division": "Juvenile Male BLUE Light", "category_id": "2815615", "mat": "3", "fight_num": "22", "fight_time": "Sun 04/12 at 04:26 PM"}, {"name": "Eduard Bodak", "team": "Versus Brazilian Jiu-Jitsu Academy", "division": "Juvenile Male BLUE Middle", "category_id": "2815617", "mat": "7", "fight_num": "20", "fight_time": "Sun 04/12 at 04:22 PM"}, {"name": "Kaua Diogo Abrantes Ribeiro", "team": "Athlas Training Team", "division": "Juvenile Male BLUE Middle", "category_id": "2815617", "mat": "7", "fight_num": "20", "fight_time": "Sun 04/12 at 04:22 PM"}, {"name": "Jack James Mitchell", "team": "Essential Jiu-Jitsu", "division": "Juvenile Male BLUE Medium Heavy", "category_id": "2815619", "mat": "1", "fight_num": "18", "fight_time": "Sun 04/12 at 04:47 PM"}, {"name": "Dylan Song Rosario", "team": "Rising Sun BJJ", "division": "Juvenile Male BLUE Medium Heavy", "category_id": "2815619", "mat": "1", "fight_num": "18", "fight_time": "Sun 04/12 at 04:47 PM"}, {"name": "Jay Anthony Toll-Santiago", "team": "Carlos Rosado - Jiu Jitsu Modern", "division": "Juvenile Male BLUE Heavy", "category_id": "2815621", "mat": "9", "fight_num": "23", "fight_time": "Sun 04/12 at 05:02 PM"}, {"name": "Matheus Martins de Aguiar Generoso", "team": "Banana Jiu-Jitsu", "division": "Juvenile Male BLUE Heavy", "category_id": "2815621", "mat": "9", "fight_num": "23", "fight_time": "Sun 04/12 at 05:02 PM"}, {"name": "Ryan Anthony Joseph Sylvia", "team": "Unity Jiu-jitsu", "division": "Juvenile Male BLUE Heavy", "category_id": "2815621", "mat": "9", "fight_num": "19", "fight_time": "Sun 04/12 at 04:41 PM"}, {"name": "David Alexander Preuss Lopes", "team": "Nova Uni\u00e3o", "division": "Juvenile Male BLUE Super Heavy", "category_id": "2815623", "mat": "6", "fight_num": "23", "fight_time": "Sun 04/12 at 04:58 PM"}, {"name": "Daniel Patrick Welsh", "team": "Tony Passos Jiu-Jitsu", "division": "Juvenile Male BLUE Super Heavy", "category_id": "2815623", "mat": "6", "fight_num": "23", "fight_time": "Sun 04/12 at 04:58 PM"}, {"name": "Niketh Luke R. Vangala", "team": "Logic", "division": "Adult Male BLUE Rooster", "category_id": "2815133", "mat": "1", "fight_num": "5", "fight_time": "Sun 04/12 at 03:11 PM"}, {"name": "Armando Salvatore Clemente", "team": "Logic", "division": "Adult Male BLUE Rooster", "category_id": "2815133", "mat": "1", "fight_num": "5", "fight_time": "Sun 04/12 at 03:11 PM"}, {"name": "Zain Ahmad", "team": "Alliance", "division": "Adult Male BLUE Rooster", "category_id": "2815133", "mat": "1", "fight_num": "1", "fight_time": "Sun 04/12 at 02:31 PM"}, {"name": "Joel Delorbe Jr.", "team": "GF Team", "division": "Adult Male BLUE Light Feather", "category_id": "2815137", "mat": "7", "fight_num": "1", "fight_time": "Sun 04/12 at 02:32 PM"}, {"name": "Bryson B Thomas", "team": "Essential Jiu-Jitsu", "division": "Adult Male BLUE Light Feather", "category_id": "2815137", "mat": "7", "fight_num": "1", "fight_time": "Sun 04/12 at 02:32 PM"}, {"name": "Nicholas Joseph Cusato", "team": "Logic", "division": "Adult Male BLUE Light Feather", "category_id": "2815137", "mat": "7", "fight_num": "16", "fight_time": "Sun 04/12 at 03:56 PM"}, {"name": "Nicola Armando Petruccelli", "team": "Malverne Monarch Jiu-Jitsu", "division": "Adult Male BLUE Light Feather", "category_id": "2815137", "mat": "7", "fight_num": "9", "fight_time": "Sun 04/12 at 03:16 PM"}, {"name": "Sebastian Joseph Stafford", "team": "North Fork Jiu-Jitsu", "division": "Adult Male BLUE Light Feather", "category_id": "2815137", "mat": "7", "fight_num": "9", "fight_time": "Sun 04/12 at 03:16 PM"}, {"name": "Dallas Aiden Henderson", "team": "RMNU Team", "division": "Adult Male BLUE Light Feather", "category_id": "2815137", "mat": "7", "fight_num": "10", "fight_time": "Sun 04/12 at 03:24 PM"}, {"name": "Carter George Valeski", "team": "Logic", "division": "Adult Male BLUE Light Feather", "category_id": "2815137", "mat": "7", "fight_num": "2", "fight_time": "Sun 04/12 at 02:39 PM"}, {"name": "Samuel Lehman", "team": "Up Top Brazilian Jiu-Jitsu", "division": "Adult Male BLUE Light Feather", "category_id": "2815137", "mat": "7", "fight_num": "7", "fight_time": "Sun 04/12 at 03:03 PM"}, {"name": "Omari Hashim Perez", "team": "Renzo Gracie", "division": "Adult Male BLUE Feather", "category_id": "2815141", "mat": "5", "fight_num": "2", "fight_time": "Sun 04/12 at 02:33 PM"}, {"name": "Aden Joel Lucero", "team": "Carlson Gracie Team", "division": "Adult Male BLUE Feather", "category_id": "2815141", "mat": "5", "fight_num": "2", "fight_time": "Sun 04/12 at 02:33 PM"}, {"name": "Andrew Duncan Fiore", "team": "Freedom Jiu-Jitsu", "division": "Adult Male BLUE Feather", "category_id": "2815141", "mat": "5", "fight_num": "3", "fight_time": "Sun 04/12 at 02:37 PM"}, {"name": "Luis Enrique Maurad", "team": "Transcend Grappling Academy", "division": "Adult Male BLUE Feather", "category_id": "2815141", "mat": "5", "fight_num": "3", "fight_time": "Sun 04/12 at 02:37 PM"}, {"name": "Lucas Amorim Sabino", "team": "Brazilian Top Team", "division": "Adult Male BLUE Feather", "category_id": "2815141", "mat": "5", "fight_num": "7", "fight_time": "Sun 04/12 at 03:14 PM"}, {"name": "Rayyan Nadeem", "team": "Crazy 88", "division": "Adult Male BLUE Feather", "category_id": "2815141", "mat": "5", "fight_num": "19", "fight_time": "Sun 04/12 at 04:21 PM"}, {"name": "Xavier Alexander Mejia-Martinez", "team": "Upper Academy Florida", "division": "Adult Male BLUE Feather", "category_id": "2815141", "mat": "5", "fight_num": "19", "fight_time": "Sun 04/12 at 04:21 PM"}, {"name": "David Leite Almeida", "team": "Renzo Gracie", "division": "Adult Male BLUE Feather", "category_id": "2815141", "mat": "5", "fight_num": "11", "fight_time": "Sun 04/12 at 03:28 PM"}, {"name": "Steven Neil Suter", "team": "Black Hole Jiu-Jitsu", "division": "Adult Male BLUE Feather", "category_id": "2815141", "mat": "5", "fight_num": "1", "fight_time": "Sun 04/12 at 02:30 PM"}, {"name": "Sebastian Enrique La Rosa", "team": "Vamos Brazilian Jiu Jitsu", "division": "Adult Male BLUE Feather", "category_id": "2815141", "mat": "5", "fight_num": "5", "fight_time": "Sun 04/12 at 03:00 PM"}, {"name": "Andrew Adolphe Meristil", "team": "Gregor Gracie Jiu-Jitsu", "division": "Adult Male BLUE Feather", "category_id": "2815141", "mat": "5", "fight_num": "8", "fight_time": "Sun 04/12 at 02:55 PM"}, {"name": "Cristian Cruz", "team": "The Vanguard Academy", "division": "Adult Male BLUE Feather", "category_id": "2815141", "mat": "5", "fight_num": "8", "fight_time": "Sun 04/12 at 02:55 PM"}, {"name": "Anthony Joseph Espino", "team": "TDBJJ", "division": "Adult Male BLUE Feather", "category_id": "2815141", "mat": "5", "fight_num": "6", "fight_time": "Sun 04/12 at 03:07 PM"}, {"name": "Michael Espinoza", "team": "Masterskya", "division": "Adult Male BLUE Feather", "category_id": "2815141", "mat": "5", "fight_num": "6", "fight_time": "Sun 04/12 at 03:07 PM"}, {"name": "Siavash Omidvar", "team": "A-Force Brazilian Jiu-Jitsu", "division": "Adult Male BLUE Light", "category_id": "2815145", "mat": "3", "fight_num": "1", "fight_time": "Sun 04/12 at 02:32 PM"}, {"name": "Mitchell Kristopher Yaggi", "team": "Ultimate MMA Training Center", "division": "Adult Male BLUE Light", "category_id": "2815145", "mat": "3", "fight_num": "1", "fight_time": "Sun 04/12 at 02:32 PM"}, {"name": "Nickolas Vasilios Karamoshos", "team": "Serra BJJ", "division": "Adult Male BLUE Light", "category_id": "2815145", "mat": "4", "fight_num": "2", "fight_time": "Sun 04/12 at 02:37 PM"}, {"name": "Jayden Marc Brown", "team": "Masterskya", "division": "Adult Male BLUE Light", "category_id": "2815145", "mat": "4", "fight_num": "2", "fight_time": "Sun 04/12 at 02:37 PM"}, {"name": "Sean Michael Anderson", "team": "Alex Humen JJ", "division": "Adult Male BLUE Light", "category_id": "2815145", "mat": "3", "fight_num": "3", "fight_time": "Sun 04/12 at 02:48 PM"}, {"name": "Pedro Cruz", "team": "BJJ - Mushin", "division": "Adult Male BLUE Light", "category_id": "2815145", "mat": "3", "fight_num": "13", "fight_time": "Sun 04/12 at 03:58 PM"}, {"name": "Aaron Jose Trujillo", "team": "Bronx Martial Arts Academy", "division": "Adult Male BLUE Light", "category_id": "2815145", "mat": "3", "fight_num": "5", "fight_time": "Sun 04/12 at 03:00 PM"}, {"name": "Lawrence David Veytsman", "team": "Caio Terra Association - New York", "division": "Adult Male BLUE Light", "category_id": "2815145", "mat": "3", "fight_num": "8", "fight_time": "Sun 04/12 at 03:17 PM"}, {"name": "Evan Michael Dunford", "team": "The Vanguard Academy", "division": "Adult Male BLUE Light", "category_id": "2815145", "mat": "", "fight_num": "", "fight_time": ""}, {"name": "John Joseph Mahoney", "team": "Essential Jiu-Jitsu", "division": "Adult Male BLUE Light", "category_id": "2815145", "mat": "", "fight_num": "", "fight_time": ""}, {"name": "Pietro Faria Gazzoni", "team": "Brazilian Top Team", "division": "Adult Male BLUE Light", "category_id": "2815145", "mat": "4", "fight_num": "3", "fight_time": "Sun 04/12 at 02:45 PM"}, {"name": "Eric Isaac Honig", "team": "Malverne Monarch Jiu-Jitsu", "division": "Adult Male BLUE Light", "category_id": "2815145", "mat": "4", "fight_num": "3", "fight_time": "Sun 04/12 at 02:45 PM"}, {"name": "Derwin D. Molina", "team": "BJJ - Mushin", "division": "Adult Male BLUE Light", "category_id": "2815145", "mat": "", "fight_num": "", "fight_time": ""}, {"name": "Jacob Steven Tuzinkiewicz", "team": "The Vanguard Academy", "division": "Adult Male BLUE Light", "category_id": "2815145", "mat": "4", "fight_num": "7", "fight_time": "Sun 04/12 at 03:11 PM"}, {"name": "Gavin Gerald Byra", "team": "Balance", "division": "Adult Male BLUE Light", "category_id": "2815145", "mat": "4", "fight_num": "13", "fight_time": "Sun 04/12 at 03:57 PM"}, {"name": "Jacob Michael Scheflan", "team": "Rising Sun BJJ", "division": "Adult Male BLUE Light", "category_id": "2815145", "mat": "4", "fight_num": "4", "fight_time": "Sun 04/12 at 02:51 PM"}, {"name": "Keven de Ara\u00fajo  Borges da Silva", "team": "TDBJJ", "division": "Adult Male BLUE Light", "category_id": "2815145", "mat": "4", "fight_num": "8", "fight_time": "Sun 04/12 at 03:22 PM"}, {"name": "Victor Abraham Camarillo Gomez", "team": "Caio Terra Association - New York", "division": "Adult Male BLUE Light", "category_id": "2815145", "mat": "", "fight_num": "", "fight_time": ""}, {"name": "Areeb Pirzada", "team": "Bronx Martial Arts Academy", "division": "Adult Male BLUE Light", "category_id": "2815145", "mat": "", "fight_num": "", "fight_time": ""}, {"name": "Charles Chiang Lee", "team": "Renzo Gracie", "division": "Adult Male BLUE Middle", "category_id": "2815149", "mat": "6", "fight_num": "1", "fight_time": "Sun 04/12 at 02:32 PM"}, {"name": "Justin L. Gaudiana", "team": "Rilion Gracie Rhode Island", "division": "Adult Male BLUE Middle", "category_id": "2815149", "mat": "6", "fight_num": "1", "fight_time": "Sun 04/12 at 02:32 PM"}, {"name": "Alabed A Taha", "team": "Rising Sun BJJ", "division": "Adult Male BLUE Middle", "category_id": "2815149", "mat": "6", "fight_num": "2", "fight_time": "Sun 04/12 at 02:40 PM"}, {"name": "Declan James Ferris", "team": "Brian Beaury Jiu-Jitsu", "division": "Adult Male BLUE Middle", "category_id": "2815149", "mat": "6", "fight_num": "2", "fight_time": "Sun 04/12 at 02:40 PM"}, {"name": "Cole Emerson Patrick", "team": "South Boston Bjj", "division": "Adult Male BLUE Middle", "category_id": "2815149", "mat": "6", "fight_num": "5", "fight_time": "Sun 04/12 at 03:00 PM"}, {"name": "Justin Alexander Purnell", "team": "Noel Smith Brazilian Jiu-Jitsu", "division": "Adult Male BLUE Middle", "category_id": "2815149", "mat": "6", "fight_num": "7", "fight_time": "Sun 04/12 at 03:05 PM"}, {"name": "Adler D Karle", "team": "Masterskya", "division": "Adult Male BLUE Middle", "category_id": "2815149", "mat": "6", "fight_num": "10", "fight_time": "Sun 04/12 at 03:28 PM"}, {"name": "Dario Humberto Molina", "team": "Renzo Gracie", "division": "Adult Male BLUE Middle", "category_id": "2815149", "mat": "6", "fight_num": "13", "fight_time": "Sun 04/12 at 03:52 PM"}, {"name": "Kevin Sadej", "team": "Up Top Brazilian Jiu-Jitsu", "division": "Adult Male BLUE Middle", "category_id": "2815149", "mat": "6", "fight_num": "3", "fight_time": "Sun 04/12 at 02:43 PM"}, {"name": "Joseph Thomas Borja", "team": "Transcend Grappling Academy", "division": "Adult Male BLUE Middle", "category_id": "2815149", "mat": "6", "fight_num": "3", "fight_time": "Sun 04/12 at 02:43 PM"}, {"name": "Marino Ginebra", "team": "South Boston Bjj", "division": "Adult Male BLUE Middle", "category_id": "2815149", "mat": "6", "fight_num": "4", "fight_time": "Sun 04/12 at 02:52 PM"}, {"name": "Juan  Pablo lopez", "team": "G.A.D./B9", "division": "Adult Male BLUE Middle", "category_id": "2815149", "mat": "6", "fight_num": "9", "fight_time": "Sun 04/12 at 03:09 PM"}, {"name": "Hugo Christian England", "team": "Alliance", "division": "Adult Male BLUE Medium Heavy", "category_id": "2815153", "mat": "7", "fight_num": "4", "fight_time": "Sun 04/12 at 02:50 PM"}, {"name": "Raffaele Joseph Lestingi", "team": "Black Hole Jiu-Jitsu", "division": "Adult Male BLUE Medium Heavy", "category_id": "2815153", "mat": "7", "fight_num": "4", "fight_time": "Sun 04/12 at 02:50 PM"}, {"name": "Gage Braxton Baker", "team": "SAS Team", "division": "Adult Male BLUE Medium Heavy", "category_id": "2815153", "mat": "", "fight_num": "", "fight_time": ""}, {"name": "Gavin Nhat Nguyen", "team": "Logic", "division": "Adult Male BLUE Medium Heavy", "category_id": "2815153", "mat": "7", "fight_num": "5", "fight_time": "Sun 04/12 at 02:51 PM"}, {"name": "Jeremy Adam Brandel", "team": "Sucker Free Jiu-Jitsu", "division": "Adult Male BLUE Medium Heavy", "category_id": "2815153", "mat": "7", "fight_num": "15", "fight_time": "Sun 04/12 at 03:51 PM"}, {"name": "Yoseph Beheshti Shirazi", "team": "Vicente Jr. Team", "division": "Adult Male BLUE Medium Heavy", "category_id": "2815153", "mat": "7", "fight_num": "15", "fight_time": "Sun 04/12 at 03:51 PM"}, {"name": "Benjamin Matthew Selya", "team": "Native Brazilian Jiu-Jitsu", "division": "Adult Male BLUE Medium Heavy", "category_id": "2815153", "mat": "7", "fight_num": "3", "fight_time": "Sun 04/12 at 02:44 PM"}, {"name": "Yonbue Caleb Goodall Tanco", "team": "Masterskya", "division": "Adult Male BLUE Medium Heavy", "category_id": "2815153", "mat": "", "fight_num": "", "fight_time": ""}, {"name": "Phillip Lars Vorbach", "team": "TDBJJ", "division": "Adult Male BLUE Medium Heavy", "category_id": "2815153", "mat": "", "fight_num": "", "fight_time": ""}, {"name": "Ericson Alexander Velasquez", "team": "Alliance", "division": "Adult Male BLUE Heavy", "category_id": "2815157", "mat": "3", "fight_num": "6", "fight_time": "Sun 04/12 at 03:03 PM"}, {"name": "Enrico Giovanni Denard", "team": "Unity Jiu-jitsu", "division": "Adult Male BLUE Heavy", "category_id": "2815157", "mat": "3", "fight_num": "6", "fight_time": "Sun 04/12 at 03:03 PM"}, {"name": "Joseph Murray Abill", "team": "Chokelab Academy", "division": "Adult Male BLUE Heavy", "category_id": "2815157", "mat": "", "fight_num": "", "fight_time": ""}, {"name": "Kyle Matthew Inlander", "team": "CheckMat", "division": "Adult Male BLUE Heavy", "category_id": "2815157", "mat": "3", "fight_num": "11", "fight_time": "Sun 04/12 at 03:40 PM"}, {"name": "Nathan Sol Parker", "team": "Renzo Gracie", "division": "Adult Male BLUE Heavy", "category_id": "2815157", "mat": "3", "fight_num": "21", "fight_time": "Sun 04/12 at 04:35 PM"}, {"name": "Thomas Paul Kruse II", "team": "TAC Team BJJ", "division": "Adult Male BLUE Heavy", "category_id": "2815157", "mat": "3", "fight_num": "21", "fight_time": "Sun 04/12 at 04:35 PM"}, {"name": "Henry Mac Callum Gregory", "team": "Alliance", "division": "Adult Male BLUE Heavy", "category_id": "2815157", "mat": "3", "fight_num": "10", "fight_time": "Sun 04/12 at 03:32 PM"}, {"name": "Jordan C. Delvalle", "team": "Mark Ramos Academy", "division": "Adult Male BLUE Heavy", "category_id": "2815157", "mat": "", "fight_num": "", "fight_time": ""}, {"name": "Jonah Harry Deykin", "team": "Alliance Marcelo Garcia", "division": "Adult Male BLUE Heavy", "category_id": "2815157", "mat": "", "fight_num": "", "fight_time": ""}, {"name": "Joseph James Ballar", "team": "Masterskya", "division": "Adult Male BLUE Super Heavy", "category_id": "2815161", "mat": "2", "fight_num": "12", "fight_time": "Sun 04/12 at 03:44 PM"}, {"name": "Elishah D. Garrett", "team": "The BJJ Lounge", "division": "Adult Male BLUE Super Heavy", "category_id": "2815161", "mat": "2", "fight_num": "12", "fight_time": "Sun 04/12 at 03:44 PM"}, {"name": "Christopher Geovanny Barreno", "team": "Noel Smith Brazilian Jiu-Jitsu", "division": "Adult Male BLUE Super Heavy", "category_id": "2815161", "mat": "2", "fight_num": "6", "fight_time": "Sun 04/12 at 03:04 PM"}, {"name": "Magomet Albotov", "team": "Gregor Gracie Jiu-Jitsu", "division": "Adult Male BLUE Ultra Heavy", "category_id": "2815165", "mat": "4", "fight_num": "12", "fight_time": "Sun 04/12 at 03:48 PM"}, {"name": "Christopher Galletta", "team": "Unity Jiu-jitsu", "division": "Adult Male BLUE Ultra Heavy", "category_id": "2815165", "mat": "4", "fight_num": "12", "fight_time": "Sun 04/12 at 03:48 PM"}, {"name": "Maxime Gauthier", "team": "Renzo Gracie", "division": "Adult Male BLUE Ultra Heavy", "category_id": "2815165", "mat": "4", "fight_num": "6", "fight_time": "Sun 04/12 at 03:04 PM"}, {"name": "Trevor Edward Reynolds", "team": "CJJ Clear Jiu-Jitsu Academy", "division": "Adult Male BLUE Ultra Heavy", "category_id": "2815165", "mat": "4", "fight_num": "9", "fight_time": "Sun 04/12 at 03:24 PM"}, {"name": "Joey Cruz Panetta", "team": "Essential Jiu-Jitsu", "division": "Adult Male PURPLE Light Feather", "category_id": "2815138", "mat": "1", "fight_num": "15", "fight_time": "Sun 04/12 at 04:05 PM"}, {"name": "Daniel Antonio Amaya", "team": "CheckMat", "division": "Adult Male PURPLE Light Feather", "category_id": "2815138", "mat": "1", "fight_num": "15", "fight_time": "Sun 04/12 at 04:05 PM"}, {"name": "Jonah Luke Kammermayer", "team": "Black Gold Jiu-Jitsu Academy", "division": "Adult Male PURPLE Light Feather", "category_id": "2815138", "mat": "1", "fight_num": "12", "fight_time": "Sun 04/12 at 03:39 PM"}, {"name": "Michael Edwin Titus", "team": "Team Forsa", "division": "Adult Male PURPLE Light Feather", "category_id": "2815138", "mat": "1", "fight_num": "11", "fight_time": "Sun 04/12 at 03:24 PM"}, {"name": "Juan J. Rodriguez", "team": "Unity Jiu-jitsu", "division": "Adult Male PURPLE Feather", "category_id": "2815142", "mat": "6", "fight_num": "18", "fight_time": "Sun 04/12 at 04:30 PM"}, {"name": "Jordan Louis Velazquez", "team": "Serra BJJ", "division": "Adult Male PURPLE Feather", "category_id": "2815142", "mat": "6", "fight_num": "18", "fight_time": "Sun 04/12 at 04:30 PM"}, {"name": "Marcus Jonathan Levy", "team": "Luiz Palhares Jiu-Jitsu", "division": "Adult Male PURPLE Feather", "category_id": "2815142", "mat": "6", "fight_num": "17", "fight_time": "Sun 04/12 at 04:27 PM"}, {"name": "Nicholas Roman Kruczkowski", "team": "Essential Jiu-Jitsu", "division": "Adult Male PURPLE Feather", "category_id": "2815142", "mat": "6", "fight_num": "14", "fight_time": "Sun 04/12 at 03:55 PM"}, {"name": "Esteban Xavier Chiliquinga Cevallos", "team": "ZM Gorilla Fight Team", "division": "Adult Male PURPLE Light", "category_id": "2815146", "mat": "2", "fight_num": "10", "fight_time": "Sun 04/12 at 03:28 PM"}, {"name": "Abdul Mateen Stevens", "team": "Unity Jiu-jitsu", "division": "Adult Male PURPLE Light", "category_id": "2815146", "mat": "2", "fight_num": "10", "fight_time": "Sun 04/12 at 03:28 PM"}, {"name": "Jack Matthew Scala", "team": "Gracie Barra", "division": "Adult Male PURPLE Light", "category_id": "2815146", "mat": "2", "fight_num": "11", "fight_time": "Sun 04/12 at 03:32 PM"}, {"name": "Samuel Ivan Thang", "team": "Brian Beaury Jiu-Jitsu", "division": "Adult Male PURPLE Light", "category_id": "2815146", "mat": "2", "fight_num": "11", "fight_time": "Sun 04/12 at 03:32 PM"}, {"name": "Bryce Allen Grantz", "team": "Standard Jiu-Jitsu", "division": "Adult Male PURPLE Light", "category_id": "2815146", "mat": "2", "fight_num": "15", "fight_time": "Sun 04/12 at 04:04 PM"}, {"name": "Daniel Grant Cohen", "team": "TAC Team BJJ", "division": "Adult Male PURPLE Light", "category_id": "2815146", "mat": "2", "fight_num": "23", "fight_time": "Sun 04/12 at 05:00 PM"}, {"name": "Manny Alexandre Esmeraldo Jr", "team": "GF Team", "division": "Adult Male PURPLE Light", "category_id": "2815146", "mat": "2", "fight_num": "16", "fight_time": "Sun 04/12 at 04:12 PM"}, {"name": "Andrew Steven Czarnecki", "team": "Cascao Jiu-Jitsu", "division": "Adult Male PURPLE Light", "category_id": "2815146", "mat": "2", "fight_num": "21", "fight_time": "Sun 04/12 at 04:51 PM"}, {"name": "Elijah E Brown", "team": "Pedro Sauer Team", "division": "Adult Male PURPLE Light", "category_id": "2815146", "mat": "", "fight_num": "", "fight_time": ""}, {"name": "Juan Omar Lopez", "team": "Masterskya", "division": "Adult Male PURPLE Light", "category_id": "2815146", "mat": "2", "fight_num": "22", "fight_time": "Sun 04/12 at 04:46 PM"}, {"name": "Eric Beaudin", "team": "Ottawa So Jiu-Jitsu", "division": "Adult Male PURPLE Middle", "category_id": "2815150", "mat": "4", "fight_num": "11", "fight_time": "Sun 04/12 at 03:38 PM"}, {"name": "Joseph Eli Reyes Aguas", "team": "Alliance", "division": "Adult Male PURPLE Middle", "category_id": "2815150", "mat": "4", "fight_num": "11", "fight_time": "Sun 04/12 at 03:38 PM"}, {"name": "Justin Marlow Luna", "team": "Mark Ramos Academy", "division": "Adult Male PURPLE Middle", "category_id": "2815150", "mat": "", "fight_num": "", "fight_time": ""}, {"name": "Miles Helcio da Silva", "team": "Double Five Highland Village", "division": "Adult Male PURPLE Middle", "category_id": "2815150", "mat": "4", "fight_num": "17", "fight_time": "Sun 04/12 at 04:22 PM"}, {"name": "Carson Daniel Canas", "team": "Essential Jiu-Jitsu", "division": "Adult Male PURPLE Middle", "category_id": "2815150", "mat": "4", "fight_num": "18", "fight_time": "Sun 04/12 at 04:26 PM"}, {"name": "Ethan M Savluk", "team": "API - Ascension Athletics", "division": "Adult Male PURPLE Middle", "category_id": "2815150", "mat": "4", "fight_num": "20", "fight_time": "Sun 04/12 at 04:45 PM"}, {"name": "Lucas Edward Johnson", "team": "North Fork Jiu-Jitsu", "division": "Adult Male PURPLE Middle", "category_id": "2815150", "mat": "4", "fight_num": "21", "fight_time": "Sun 04/12 at 04:47 PM"}, {"name": "Robert Halligan Riordan", "team": "TDBJJ", "division": "Adult Male PURPLE Middle", "category_id": "2815150", "mat": "", "fight_num": "", "fight_time": ""}, {"name": "Pedro N Paez", "team": "Renzo Gracie", "division": "Adult Male PURPLE Middle", "category_id": "2815150", "mat": "4", "fight_num": "14", "fight_time": "Sun 04/12 at 04:04 PM"}, {"name": "Dymytriy Oleksiyovych Zyunkin", "team": "Unity Jiu-jitsu", "division": "Adult Male PURPLE Medium Heavy", "category_id": "2815154", "mat": "7", "fight_num": "19", "fight_time": "Sun 04/12 at 04:28 PM"}, {"name": "Jalal Joseph Sawas", "team": "Transcend Grappling Academy", "division": "Adult Male PURPLE Medium Heavy", "category_id": "2815154", "mat": "7", "fight_num": "19", "fight_time": "Sun 04/12 at 04:28 PM"}, {"name": "Anthony Joseph Sakovsky", "team": "The Nexus Collective", "division": "Adult Male PURPLE Medium Heavy", "category_id": "2815154", "mat": "7", "fight_num": "13", "fight_time": "Sun 04/12 at 03:37 PM"}, {"name": "Varney Fila Sando Jr", "team": "Renzo Gracie", "division": "Adult Male PURPLE Medium Heavy", "category_id": "2815154", "mat": "7", "fight_num": "18", "fight_time": "Sun 04/12 at 04:12 PM"}, {"name": "Tavon Latrell Nevins", "team": "Gracie Barra", "division": "Adult Male PURPLE Heavy", "category_id": "2815158", "mat": "5", "fight_num": "4", "fight_time": "Sun 04/12 at 02:51 PM"}, {"name": "Gutemberg D. Jean Baptiste", "team": "Renzo Gracie", "division": "Adult Male PURPLE Heavy", "category_id": "2815158", "mat": "5", "fight_num": "4", "fight_time": "Sun 04/12 at 02:51 PM"}, {"name": "Darwin Agustin Recalde Canabe", "team": "Mark Ramos Academy", "division": "Adult Male PURPLE Heavy", "category_id": "2815158", "mat": "5", "fight_num": "18", "fight_time": "Sun 04/12 at 04:13 PM"}, {"name": "John Reese Zimmerman", "team": "The Vanguard Academy", "division": "Adult Male PURPLE Heavy", "category_id": "2815158", "mat": "5", "fight_num": "18", "fight_time": "Sun 04/12 at 04:13 PM"}, {"name": "Hayden David Lawrence Sutorius McInrue", "team": "Gracie Barra", "division": "Adult Male PURPLE Heavy", "category_id": "2815158", "mat": "5", "fight_num": "14", "fight_time": "Sun 04/12 at 03:49 PM"}, {"name": "Austin Thomas Serra", "team": "Freedom Jiu-Jitsu", "division": "Adult Male PURPLE Super Heavy", "category_id": "2815162", "mat": "3", "fight_num": "17", "fight_time": "Sun 04/12 at 04:17 PM"}, {"name": "Kennedy Pereira de Miranda", "team": "Cesario Brazilian Jiu Jitsu Team", "division": "Adult Male PURPLE Super Heavy", "category_id": "2815162", "mat": "3", "fight_num": "17", "fight_time": "Sun 04/12 at 04:17 PM"}, {"name": "Brady Daniel Quinlan", "team": "Frankie Passos Academy", "division": "Adult Male PURPLE Super Heavy", "category_id": "2815162", "mat": "3", "fight_num": "7", "fight_time": "Sun 04/12 at 03:12 PM"}, {"name": "Joao Gabriel Back da Trindade", "team": "GF Team", "division": "Adult Male PURPLE Ultra Heavy", "category_id": "2815166", "mat": "1", "fight_num": "13", "fight_time": "Sun 04/12 at 03:50 PM"}, {"name": "Michael Joseph Spark", "team": "Essential Jiu-Jitsu", "division": "Adult Male PURPLE Ultra Heavy", "category_id": "2815166", "mat": "1", "fight_num": "13", "fight_time": "Sun 04/12 at 03:50 PM"}, {"name": "Renan Arnoldo Quintanilla", "team": "10th Planet Denver", "division": "Adult Male BROWN Light Feather", "category_id": "2815139", "mat": "7", "fight_num": "22", "fight_time": "Sun 04/12 at 04:50 PM"}, {"name": "Max Joseph Greenberg", "team": "TDBJJ", "division": "Adult Male BROWN Light Feather", "category_id": "2815139", "mat": "7", "fight_num": "22", "fight_time": "Sun 04/12 at 04:50 PM"}, {"name": "Daniel Fernandes de Sousa Guerra", "team": "Alliance", "division": "Adult Male BROWN Light Feather", "category_id": "2815139", "mat": "7", "fight_num": "21", "fight_time": "Sun 04/12 at 04:03 PM"}, {"name": "Brandon Thomas Bigelow", "team": "Rising Sun BJJ", "division": "Adult Male BROWN Feather", "category_id": "2815143", "mat": "1", "fight_num": "21", "fight_time": "Sun 04/12 at 05:01 PM"}, {"name": "James Joseph Vanosdol", "team": "10th Planet Finishers", "division": "Adult Male BROWN Feather", "category_id": "2815143", "mat": "1", "fight_num": "19", "fight_time": "Sun 04/12 at 05:01 PM"}, {"name": "Nicholas M. Ortiz", "team": "BJJ - Mushin", "division": "Adult Male BROWN Feather", "category_id": "2815143", "mat": "1", "fight_num": "19", "fight_time": "Sun 04/12 at 05:01 PM"}, {"name": "Antony Edward Salgado", "team": "Caio Terra Academy - Alexandria", "division": "Adult Male BROWN Feather", "category_id": "2815143", "mat": "1", "fight_num": "16", "fight_time": "Sun 04/12 at 04:32 PM"}, {"name": "Joshua Benjamin Hammaker", "team": "TAC Team BJJ", "division": "Adult Male BROWN Light", "category_id": "2815147", "mat": "5", "fight_num": "10", "fight_time": "Sun 04/12 at 03:25 PM"}, {"name": "Adam James", "team": "Action & Reaction MMA Toronto", "division": "Adult Male BROWN Light", "category_id": "2815147", "mat": "5", "fight_num": "10", "fight_time": "Sun 04/12 at 03:25 PM"}, {"name": "Bailey Alexander Cohen", "team": "Unity Jiu-jitsu", "division": "Adult Male BROWN Light", "category_id": "2815147", "mat": "5", "fight_num": "25", "fight_time": "Sun 04/12 at 05:21 PM"}, {"name": "Alexander Connor Makein", "team": "API - Ascension Athletics", "division": "Adult Male BROWN Light", "category_id": "2815147", "mat": "5", "fight_num": "25", "fight_time": "Sun 04/12 at 05:21 PM"}, {"name": "Dylan Matthew O'Regan", "team": "Carlos Rosado - Jiu Jitsu Modern", "division": "Adult Male BROWN Light", "category_id": "2815147", "mat": "5", "fight_num": "20", "fight_time": "Sun 04/12 at 04:29 PM"}, {"name": "Grant Lanada Tran", "team": "Brasa Caio Terra", "division": "Adult Male BROWN Light", "category_id": "2815147", "mat": "5", "fight_num": "26", "fight_time": "Sun 04/12 at 05:31 PM"}, {"name": "Joseph Ernesto Chimbolema Morocho", "team": "Alliance", "division": "Adult Male BROWN Light", "category_id": "2815147", "mat": "5", "fight_num": "17", "fight_time": "Sun 04/12 at 04:08 PM"}, {"name": "Kyle Abad Bhojwani", "team": "Alliance", "division": "Adult Male BROWN Middle", "category_id": "2815151", "mat": "6", "fight_num": "22", "fight_time": "Sun 04/12 at 04:53 PM"}, {"name": "Sebastian Gino Silva-Baranchuk", "team": "Caio Terra Association - New York", "division": "Adult Male BROWN Middle", "category_id": "2815151", "mat": "6", "fight_num": "22", "fight_time": "Sun 04/12 at 04:53 PM"}, {"name": "Jos\u00e9 Arthur Santiago Costa", "team": "Banana Jiu-Jitsu", "division": "Adult Male BROWN Middle", "category_id": "2815151", "mat": "6", "fight_num": "16", "fight_time": "Sun 04/12 at 04:28 PM"}, {"name": "Kevin Acosta", "team": "Unity Jiu-jitsu", "division": "Adult Male BROWN Middle", "category_id": "2815151", "mat": "6", "fight_num": "19", "fight_time": "Sun 04/12 at 04:36 PM"}, {"name": "Lucas Anthony Strassburger", "team": "Vicente Jr. Team", "division": "Adult Male BROWN Medium Heavy", "category_id": "2815155", "mat": "8", "fight_num": "22", "fight_time": "Sun 04/12 at 04:42 PM"}, {"name": "Guilherme Santos do Nascimento", "team": "GF Team", "division": "Adult Male BROWN Medium Heavy", "category_id": "2815155", "mat": "8", "fight_num": "22", "fight_time": "Sun 04/12 at 04:42 PM"}, {"name": "Christopher Foy", "team": "Sampa BJJ Canada", "division": "Adult Male BROWN Medium Heavy", "category_id": "2815155", "mat": "8", "fight_num": "17", "fight_time": "Sun 04/12 at 03:58 PM"}, {"name": "Nicholas Alan Newman", "team": "Haven Jiu-Jitsu", "division": "Adult Male BROWN Heavy", "category_id": "2815159", "mat": "", "fight_num": "", "fight_time": ""}, {"name": "Cody Christopher Pasielski", "team": "Abmar Barbosa Association", "division": "Adult Male BROWN Super Heavy", "category_id": "2815163", "mat": "9", "fight_num": "22", "fight_time": "Sun 04/12 at 04:59 PM"}, {"name": "Omar Tariq N. Nada", "team": "Unity Jiu-jitsu", "division": "Adult Male BROWN Super Heavy", "category_id": "2815163", "mat": "9", "fight_num": "22", "fight_time": "Sun 04/12 at 04:59 PM"}, {"name": "Vincent P Corrado", "team": "Unity Jiu-jitsu", "division": "Adult Male BROWN Ultra Heavy", "category_id": "2815167", "mat": "", "fight_num": "", "fight_time": ""}, {"name": "Christopher Duyquan Tran", "team": "Crazy 88", "division": "Adult Male BLACK Light Feather", "category_id": "2815140", "mat": "1", "fight_num": "7", "fight_time": "Sun 04/12 at 03:20 PM"}, {"name": "Aniel  Bonifacio Candido", "team": "GF Team", "division": "Adult Male BLACK Light Feather", "category_id": "2815140", "mat": "1", "fight_num": "7", "fight_time": "Sun 04/12 at 03:20 PM"}, {"name": "Ricardo Rodrigues Silva", "team": "A-Force Brazilian Jiu-Jitsu", "division": "Adult Male BLACK Light Feather", "category_id": "2815140", "mat": "1", "fight_num": "2", "fight_time": "Sun 04/12 at 02:57 PM"}, {"name": "John Eugene Stapleton", "team": "API - Ascension Athletics", "division": "Adult Male BLACK Light Feather", "category_id": "2815140", "mat": "1", "fight_num": "4", "fight_time": "Sun 04/12 at 03:01 PM"}, {"name": "Sidemar Honorio", "team": "Renzo Gracie", "division": "Adult Male BLACK Feather", "category_id": "2815144", "mat": "2", "fight_num": "1", "fight_time": "Sun 04/12 at 02:34 PM"}, {"name": "Andr\u00e9s Fern\u00e1ndez Calderon", "team": "Silver Fox BJJ International", "division": "Adult Male BLACK Feather", "category_id": "2815144", "mat": "2", "fight_num": "1", "fight_time": "Sun 04/12 at 02:34 PM"}, {"name": "Lucas Gabriel Bianco do Amaral", "team": "Strong Inside Jiu-Jitsu Studio", "division": "Adult Male BLACK Light", "category_id": "2815148", "mat": "9", "fight_num": "3", "fight_time": "Sun 04/12 at 02:53 PM"}, {"name": "Zamir Alexander Moreno J\u00e1come", "team": "ZM Gorilla Fight Team", "division": "Adult Male BLACK Light", "category_id": "2815148", "mat": "9", "fight_num": "3", "fight_time": "Sun 04/12 at 02:53 PM"}, {"name": "Weiss Sakhizada", "team": "Sucker Free Jiu-Jitsu", "division": "Adult Male BLACK Middle", "category_id": "2815152", "mat": "2", "fight_num": "7", "fight_time": "Sun 04/12 at 02:56 PM"}, {"name": "Serge Joseph Severenchuk", "team": "Alliance", "division": "Adult Male BLACK Middle", "category_id": "2815152", "mat": "2", "fight_num": "2", "fight_time": "Sun 04/12 at 02:38 PM"}, {"name": "Michael Robert Francis-Sheehan", "team": "Jiu-Jitsu For Life Canada", "division": "Adult Male BLACK Middle", "category_id": "2815152", "mat": "2", "fight_num": "4", "fight_time": "Sun 04/12 at 02:56 PM"}, {"name": "Thomas Kubacki", "team": "TAC Team BJJ", "division": "Adult Male BLACK Medium Heavy", "category_id": "2815156", "mat": "2", "fight_num": "3", "fight_time": "Sun 04/12 at 02:56 PM"}, {"name": "Sebastian Rodriguez Williams", "team": "Unity Jiu-jitsu", "division": "Adult Male BLACK Medium Heavy", "category_id": "2815156", "mat": "2", "fight_num": "3", "fight_time": "Sun 04/12 at 02:56 PM"}, {"name": "Felipe Cesar Silva", "team": "Unity Jiu-jitsu", "division": "Adult Male BLACK Heavy", "category_id": "2815160", "mat": "9", "fight_num": "5", "fight_time": "Sun 04/12 at 03:18 PM"}, {"name": "Hugh McKenna", "team": "Masterskya", "division": "Adult Male BLACK Heavy", "category_id": "2815160", "mat": "9", "fight_num": "5", "fight_time": "Sun 04/12 at 03:18 PM"}, {"name": "Roberto Carlos Callejas Saballos", "team": "Fernando Moya Jiu-Jitsu Academy", "division": "Adult Male BLACK Heavy", "category_id": "2815160", "mat": "9", "fight_num": "2", "fight_time": "Sun 04/12 at 02:43 PM"}, {"name": "Daniel Ni\u00f1o de Rivera Garcia", "team": "Daniri Jiu-Jitsu", "division": "Adult Male BLACK Heavy", "category_id": "2815160", "mat": "9", "fight_num": "1", "fight_time": "Sun 04/12 at 02:42 PM"}, {"name": "Kyle Edmund Myers", "team": "SAS Team BJJ", "division": "Adult Male BLACK Super Heavy", "category_id": "2815164", "mat": "9", "fight_num": "4", "fight_time": "Sun 04/12 at 03:07 PM"}, {"name": "Sebastian Bishoy Morcos Attard", "team": "LEAD BJJ", "division": "Adult Male BLACK Super Heavy", "category_id": "2815164", "mat": "9", "fight_num": "4", "fight_time": "Sun 04/12 at 03:07 PM"}, {"name": "Gabriel Santos de Oliveira", "team": "Campe\u00e3o United Jiu-Jitsu", "division": "Adult Male BLACK Ultra Heavy", "category_id": "2815168", "mat": "", "fight_num": "", "fight_time": ""}, {"name": "Kyle Edmund Myers", "team": "SAS Team BJJ", "division": "Adult Male BLACK Open Class", "category_id": "2815711", "mat": "1", "fight_num": "31", "fight_time": "Sun 04/12 at 06:07 PM"}, {"name": "Zamir Alexander Moreno J\u00e1come", "team": "ZM Gorilla Fight Team", "division": "Adult Male BLACK Open Class", "category_id": "2815711", "mat": "1", "fight_num": "31", "fight_time": "Sun 04/12 at 06:07 PM"}, {"name": "Roberto Carlos Callejas Saballos", "team": "Fernando Moya Jiu-Jitsu Academy", "division": "Adult Male BLACK Open Class", "category_id": "2815711", "mat": "1", "fight_num": "32", "fight_time": "Sun 04/12 at 06:19 PM"}, {"name": "Weiss Sakhizada", "team": "Sucker Free Jiu-Jitsu", "division": "Adult Male BLACK Open Class", "category_id": "2815711", "mat": "1", "fight_num": "32", "fight_time": "Sun 04/12 at 06:19 PM"}, {"name": "Gabriel Santos de Oliveira", "team": "Campe\u00e3o United Jiu-Jitsu", "division": "Adult Male BLACK Open Class", "category_id": "2815711", "mat": "1", "fight_num": "33", "fight_time": "Sun 04/12 at 06:31 PM"}, {"name": "Sebastian Bishoy Morcos Attard", "team": "LEAD BJJ", "division": "Adult Male BLACK Open Class", "category_id": "2815711", "mat": "1", "fight_num": "34", "fight_time": "Sun 04/12 at 06:43 PM"}, {"name": "Sean Patrick Finn", "team": "Breathe Jiu-Jitsu", "division": "Master 1 Male BLUE Light", "category_id": "2815213", "mat": "4", "fight_num": "25", "fight_time": "Sun 04/12 at 05:23 PM"}, {"name": "Vincenzo Giovanni Recine", "team": "Renzo Gracie", "division": "Master 1 Male BLUE Light", "category_id": "2815213", "mat": "4", "fight_num": "25", "fight_time": "Sun 04/12 at 05:23 PM"}, {"name": "Nicholas William Antosh", "team": "SAS Team BJJ", "division": "Master 1 Male BLUE Light", "category_id": "2815213", "mat": "4", "fight_num": "29", "fight_time": "Sun 04/12 at 05:45 PM"}, {"name": "Elliot Stoddard Frank", "team": "Clockwork Jiu-Jitsu", "division": "Master 1 Male BLUE Light", "category_id": "2815213", "mat": "4", "fight_num": "27", "fight_time": "Sun 04/12 at 05:30 PM"}, {"name": "Anthony Joshua Ortiz", "team": "Renzo Gracie", "division": "Master 1 Male BLUE Light", "category_id": "2815213", "mat": "4", "fight_num": "22", "fight_time": "Sun 04/12 at 04:54 PM"}, {"name": "Stephan J Bogardus", "team": "North Fork Jiu-Jitsu", "division": "Master 1 Male BLUE Middle", "category_id": "2815217", "mat": "3", "fight_num": "25", "fight_time": "Sun 04/12 at 04:55 PM"}, {"name": "Anderson Soares da Silva Santos", "team": "Grip Brazilian Jiu-Jitsu Headquarters", "division": "Master 1 Male BLUE Middle", "category_id": "2815217", "mat": "3", "fight_num": "25", "fight_time": "Sun 04/12 at 04:55 PM"}, {"name": "Francisco Giorgio Jr.", "team": "Sucker Free Jiu-Jitsu", "division": "Master 1 Male BLUE Medium Heavy", "category_id": "2815221", "mat": "9", "fight_num": "26", "fight_time": "Sun 04/12 at 05:22 PM"}, {"name": "Samuel F Izzarelli III", "team": "Surfight Jiu-Jitsu", "division": "Master 1 Male BLUE Medium Heavy", "category_id": "2815221", "mat": "9", "fight_num": "24", "fight_time": "Sun 04/12 at 05:15 PM"}, {"name": "Oluboni Shammah O Agbaniyaka", "team": "The Ultimate Grappling Club", "division": "Master 1 Male BLUE Medium Heavy", "category_id": "2815221", "mat": "9", "fight_num": "24", "fight_time": "Sun 04/12 at 05:15 PM"}, {"name": "Donald P. Rogers", "team": "Breathe Jiu-Jitsu", "division": "Master 1 Male BLUE Medium Heavy", "category_id": "2815221", "mat": "9", "fight_num": "21", "fight_time": "Sun 04/12 at 04:57 PM"}, {"name": "Joseph Edward Leeman", "team": "Renzo Gracie", "division": "Master 1 Male BLUE Heavy", "category_id": "2815225", "mat": "3", "fight_num": "27", "fight_time": "Sun 04/12 at 05:18 PM"}, {"name": "Anthony Ray Steward", "team": "Renzo Gracie", "division": "Master 1 Male BLUE Heavy", "category_id": "2815225", "mat": "3", "fight_num": "27", "fight_time": "Sun 04/12 at 05:18 PM"}, {"name": "Reza Rezaye", "team": "Breakfast Club Jiu-Jitsu", "division": "Master 1 Male PURPLE Feather", "category_id": "2815210", "mat": "2", "fight_num": "24", "fight_time": "Sun 04/12 at 05:15 PM"}, {"name": "Jonathan James Bianco", "team": "Renzo Gracie", "division": "Master 1 Male PURPLE Feather", "category_id": "2815210", "mat": "2", "fight_num": "24", "fight_time": "Sun 04/12 at 05:15 PM"}, {"name": "Abou-Sow Yao Nkromah", "team": "Renzo Gracie", "division": "Master 1 Male PURPLE Light", "category_id": "2815214", "mat": "5", "fight_num": "22", "fight_time": "Sun 04/12 at 04:53 PM"}, {"name": "David James Malone", "team": "TAC Team BJJ", "division": "Master 1 Male PURPLE Light", "category_id": "2815214", "mat": "5", "fight_num": "22", "fight_time": "Sun 04/12 at 04:53 PM"}, {"name": "Dominick Anthony Biondo", "team": "R1NG BJJ", "division": "Master 1 Male PURPLE Light", "category_id": "2815214", "mat": "5", "fight_num": "26", "fight_time": "Sun 04/12 at 05:25 PM"}, {"name": "Brendan Christopher Loska", "team": "Team Juc\u00e3o", "division": "Master 1 Male PURPLE Light", "category_id": "2815214", "mat": "", "fight_num": "", "fight_time": ""}, {"name": "Kyle C Wood", "team": "Carlson Gracie Team", "division": "Master 1 Male PURPLE Light", "category_id": "2815214", "mat": "5", "fight_num": "24", "fight_time": "Sun 04/12 at 05:10 PM"}, {"name": "Nicholas William Princiotta", "team": "CheckMat", "division": "Master 1 Male PURPLE Middle", "category_id": "2815218", "mat": "3", "fight_num": "26", "fight_time": "Sun 04/12 at 05:10 PM"}, {"name": "Anthony G. Cangemi", "team": "Masterskya", "division": "Master 1 Male PURPLE Middle", "category_id": "2815218", "mat": "3", "fight_num": "26", "fight_time": "Sun 04/12 at 05:10 PM"}, {"name": "Weylin Mccall Long", "team": "BJJ Revolution Team", "division": "Master 1 Male PURPLE Middle", "category_id": "2815218", "mat": "3", "fight_num": "29", "fight_time": "Sun 04/12 at 05:32 PM"}, {"name": "Luis Adri\u00e1n Chiliquinga Cevallos", "team": "ZM Gorilla Fight Team", "division": "Master 1 Male PURPLE Middle", "category_id": "2815218", "mat": "3", "fight_num": "29", "fight_time": "Sun 04/12 at 05:32 PM"}, {"name": "Stephen Benjamin Spencer", "team": "Masterskya", "division": "Master 1 Male PURPLE Medium Heavy", "category_id": "2815222", "mat": "4", "fight_num": "30", "fight_time": "Sun 04/12 at 05:42 PM"}, {"name": "Lewis G. Reynoso", "team": "Bronx Martial Arts Academy", "division": "Master 1 Male PURPLE Medium Heavy", "category_id": "2815222", "mat": "4", "fight_num": "19", "fight_time": "Sun 04/12 at 04:38 PM"}, {"name": "Mayid Abdol Kader", "team": "Standard Jiu-Jitsu", "division": "Master 1 Male PURPLE Medium Heavy", "category_id": "2815222", "mat": "4", "fight_num": "27", "fight_time": "Sun 04/12 at 05:19 PM"}, {"name": "Steven J Valentine", "team": "Gtjjteam", "division": "Master 1 Male PURPLE Medium Heavy", "category_id": "2815222", "mat": "4", "fight_num": "27", "fight_time": "Sun 04/12 at 05:19 PM"}, {"name": "Emanuel Antonio Delgado", "team": "Ares BJJ", "division": "Master 1 Male PURPLE Heavy", "category_id": "2815226", "mat": "6", "fight_num": "24", "fight_time": "Sun 04/12 at 05:05 PM"}, {"name": "Brandon S. Vetere", "team": "Dan Covel Jiu-Jitsu", "division": "Master 1 Male PURPLE Heavy", "category_id": "2815226", "mat": "6", "fight_num": "24", "fight_time": "Sun 04/12 at 05:05 PM"}, {"name": "Thomas Michael Pirrone", "team": "Carlos Rosado - Jiu Jitsu Modern", "division": "Master 1 Male BROWN Feather", "category_id": "2815211", "mat": "1", "fight_num": "27", "fight_time": "Sun 04/12 at 05:36 PM"}, {"name": "Oliver Enrique Lopez", "team": "Masterskya", "division": "Master 1 Male BROWN Feather", "category_id": "2815211", "mat": "1", "fight_num": "27", "fight_time": "Sun 04/12 at 05:36 PM"}, {"name": "Edison Fabricio Rodriguez Pinos", "team": "Unity Jiu-jitsu", "division": "Master 1 Male BROWN Feather", "category_id": "2815211", "mat": "1", "fight_num": "29", "fight_time": "Sun 04/12 at 05:51 PM"}, {"name": "Christopher Lee", "team": "Crazy 88", "division": "Master 1 Male BROWN Feather", "category_id": "2815211", "mat": "1", "fight_num": "29", "fight_time": "Sun 04/12 at 05:51 PM"}, {"name": "Renxuan Liu", "team": "Alliance", "division": "Master 1 Male BROWN Light", "category_id": "2815215", "mat": "4", "fight_num": "24", "fight_time": "Sun 04/12 at 05:15 PM"}, {"name": "Ryan Cass Waldron", "team": "Cascao Jiu-Jitsu", "division": "Master 1 Male BROWN Light", "category_id": "2815215", "mat": "4", "fight_num": "24", "fight_time": "Sun 04/12 at 05:15 PM"}, {"name": "Juhyun Chun", "team": "Alliance", "division": "Master 1 Male BROWN Middle", "category_id": "2815219", "mat": "2", "fight_num": "27", "fight_time": "Sun 04/12 at 05:17 PM"}, {"name": "William Harry McCarthy", "team": "Masterskya", "division": "Master 1 Male BROWN Middle", "category_id": "2815219", "mat": "2", "fight_num": "27", "fight_time": "Sun 04/12 at 05:17 PM"}, {"name": "Michael Louis Roselli", "team": "Carlos Rosado - Jiu Jitsu Modern", "division": "Master 1 Male BROWN Heavy", "category_id": "2815227", "mat": "6", "fight_num": "30", "fight_time": "Sun 04/12 at 05:51 PM"}, {"name": "Robert Bash Rigilano", "team": "The Jiu-Jitsu Mill", "division": "Master 1 Male BROWN Heavy", "category_id": "2815227", "mat": "6", "fight_num": "30", "fight_time": "Sun 04/12 at 05:51 PM"}, {"name": "David B. Zennario", "team": "Vicente Jr. Team", "division": "Master 1 Male BLACK Rooster", "category_id": "2815204", "mat": "", "fight_num": "", "fight_time": ""}, {"name": "Daniel Michael Stapinski", "team": "Renzo Gracie", "division": "Master 1 Male BLACK Light", "category_id": "2815216", "mat": "8", "fight_num": "2", "fight_time": "Sun 04/12 at 02:28 PM"}, {"name": "Frank Adam Rosenthal", "team": "Phantom Ghost Penthouse", "division": "Master 1 Male BLACK Light", "category_id": "2815216", "mat": "8", "fight_num": "2", "fight_time": "Sun 04/12 at 02:28 PM"}, {"name": "Elton Cau\u00e3 Rodrigues Nantes", "team": "TAM -  Team Alpha BJJ", "division": "Master 1 Male BLACK Middle", "category_id": "2815220", "mat": "8", "fight_num": "4", "fight_time": "Sun 04/12 at 02:44 PM"}, {"name": "Shane Patrick O'Reilly", "team": "Brazilian Top Team", "division": "Master 1 Male BLACK Middle", "category_id": "2815220", "mat": "8", "fight_num": "4", "fight_time": "Sun 04/12 at 02:44 PM"}, {"name": "Rory T Connors", "team": "Connors MMA", "division": "Master 1 Male BLACK Middle", "category_id": "2815220", "mat": "8", "fight_num": "9", "fight_time": "Sun 04/12 at 03:03 PM"}, {"name": "Joseph Anthony Solecki", "team": "Solecki Jiu-Jitsu", "division": "Master 1 Male BLACK Middle", "category_id": "2815220", "mat": "8", "fight_num": "9", "fight_time": "Sun 04/12 at 03:03 PM"}, {"name": "Jo\u00e3o Lucas de Faria", "team": "GF Team", "division": "Master 1 Male BLACK Middle", "category_id": "2815220", "mat": "8", "fight_num": "1", "fight_time": "Sun 04/12 at 02:20 PM"}, {"name": "Anthony Maurice Patrick", "team": "Yamasaki Academy", "division": "Master 1 Male BLACK Middle", "category_id": "2815220", "mat": "8", "fight_num": "3", "fight_time": "Sun 04/12 at 02:36 PM"}, {"name": "Jesse P. Cahill", "team": "Renzo Gracie", "division": "Master 1 Male BLACK Medium Heavy", "category_id": "2815224", "mat": "8", "fight_num": "10", "fight_time": "Sun 04/12 at 03:06 PM"}, {"name": "Diogo Felipe dos Santos Oliveira", "team": "Summit Jiu-Jitsu", "division": "Master 1 Male BLACK Medium Heavy", "category_id": "2815224", "mat": "8", "fight_num": "10", "fight_time": "Sun 04/12 at 03:06 PM"}, {"name": "Keelan James Berg", "team": "Alliance", "division": "Master 1 Male BLACK Heavy", "category_id": "2815228", "mat": "8", "fight_num": "12", "fight_time": "Sun 04/12 at 03:20 PM"}, {"name": "Andrew Steven G. Marrero", "team": "Kore BJJ & MMA", "division": "Master 1 Male BLACK Heavy", "category_id": "2815228", "mat": "8", "fight_num": "12", "fight_time": "Sun 04/12 at 03:20 PM"}, {"name": "Reinaldo Luiz da Costa Souza", "team": "Brazilian Top Team", "division": "Master 1 Male BLACK Super Heavy", "category_id": "2815232", "mat": "", "fight_num": "", "fight_time": ""}, {"name": "Colin James Gironda", "team": "Black Hole Jiu-Jitsu", "division": "Master 1 Male BLACK Ultra Heavy", "category_id": "2815236", "mat": "9", "fight_num": "7", "fight_time": "Sun 04/12 at 03:35 PM"}, {"name": "Lucas Cezario Silva", "team": "ADJJ", "division": "Master 1 Male BLACK Ultra Heavy", "category_id": "2815236", "mat": "9", "fight_num": "7", "fight_time": "Sun 04/12 at 03:35 PM"}, {"name": "Lawrence H Ayala Pacheco", "team": "R1NG BJJ", "division": "Master 2 Male BLUE Light", "category_id": "2815281", "mat": "7", "fight_num": "23", "fight_time": "Sun 04/12 at 04:55 PM"}, {"name": "Franklin Armando Lopez Chavez", "team": "GF Team", "division": "Master 2 Male BLUE Light", "category_id": "2815281", "mat": "7", "fight_num": "23", "fight_time": "Sun 04/12 at 04:55 PM"}, {"name": "Peter Park", "team": "Carlos Rosado - Jiu Jitsu Modern", "division": "Master 2 Male BLUE Light", "category_id": "2815281", "mat": "7", "fight_num": "25", "fight_time": "Sun 04/12 at 05:09 PM"}, {"name": "Roman Mizerota", "team": "GMAC", "division": "Master 2 Male BLUE Heavy", "category_id": "2815293", "mat": "1", "fight_num": "24", "fight_time": "Sun 04/12 at 05:12 PM"}, {"name": "Jared Michael Sachs", "team": "Renzo Gracie", "division": "Master 2 Male BLUE Heavy", "category_id": "2815293", "mat": "1", "fight_num": "24", "fight_time": "Sun 04/12 at 05:12 PM"}, {"name": "Ramon G. Frazier", "team": "Renzo Gracie", "division": "Master 2 Male BLUE Heavy", "category_id": "2815293", "mat": "1", "fight_num": "20", "fight_time": "Sun 04/12 at 05:02 PM"}, {"name": "Louis A. Maldarelli Jr.", "team": "Long Island MMA", "division": "Master 2 Male BLUE Ultra Heavy", "category_id": "2815301", "mat": "3", "fight_num": "28", "fight_time": "Sun 04/12 at 05:25 PM"}, {"name": "Richard Paul Connell III", "team": "Brian Beaury Jiu-Jitsu", "division": "Master 2 Male BLUE Ultra Heavy", "category_id": "2815301", "mat": "3", "fight_num": "28", "fight_time": "Sun 04/12 at 05:25 PM"}, {"name": "Jose Antonio Torres", "team": "Carlos Rosado - Jiu Jitsu Modern", "division": "Master 2 Male PURPLE Light Feather", "category_id": "2815274", "mat": "2", "fight_num": "25", "fight_time": "Sun 04/12 at 05:09 PM"}, {"name": "Toshio Taguchi", "team": "Gracie Barra", "division": "Master 2 Male PURPLE Light Feather", "category_id": "2815274", "mat": "2", "fight_num": "25", "fight_time": "Sun 04/12 at 05:09 PM"}, {"name": "Christopher M. Martino-Lieberz", "team": "Masterskya", "division": "Master 2 Male PURPLE Light", "category_id": "2815282", "mat": "6", "fight_num": "29", "fight_time": "Sun 04/12 at 05:42 PM"}, {"name": "Sean Patrick Lavelle", "team": "USA Onyx Combat Sports", "division": "Master 2 Male PURPLE Light", "category_id": "2815282", "mat": "6", "fight_num": "29", "fight_time": "Sun 04/12 at 05:42 PM"}, {"name": "Yuri A. DeBrito", "team": "Gracie Barra", "division": "Master 2 Male PURPLE Heavy", "category_id": "2815294", "mat": "", "fight_num": "", "fight_time": ""}, {"name": "Jason A. Magee", "team": "Sucker Free Jiu-Jitsu", "division": "Master 2 Male PURPLE Ultra Heavy", "category_id": "2815302", "mat": "9", "fight_num": "27", "fight_time": "Sun 04/12 at 05:29 PM"}, {"name": "Gabriel Estadella", "team": "Park Slope Brazilian Jiu-Jitsu", "division": "Master 2 Male PURPLE Ultra Heavy", "category_id": "2815302", "mat": "9", "fight_num": "27", "fight_time": "Sun 04/12 at 05:29 PM"}, {"name": "Iurii Khoruzhyi", "team": "Renzo Gracie", "division": "Master 2 Male PURPLE Ultra Heavy", "category_id": "2815302", "mat": "9", "fight_num": "30", "fight_time": "Sun 04/12 at 05:50 PM"}, {"name": "Christopher Soupras", "team": "Tri-Star Montreal", "division": "Master 2 Male BROWN Light", "category_id": "2815283", "mat": "3", "fight_num": "30", "fight_time": "Sun 04/12 at 05:40 PM"}, {"name": "Sean Quigley Harris", "team": "Vicente Jr. Team", "division": "Master 2 Male BROWN Light", "category_id": "2815283", "mat": "3", "fight_num": "30", "fight_time": "Sun 04/12 at 05:40 PM"}, {"name": "Guillaume Bernard-Paquin", "team": "Team OJJ Canada", "division": "Master 2 Male BROWN Light", "category_id": "2815283", "mat": "3", "fight_num": "32", "fight_time": "Sun 04/12 at 05:55 PM"}, {"name": "David Tran", "team": "Vicente Jr. Team", "division": "Master 2 Male BROWN Middle", "category_id": "2815287", "mat": "5", "fight_num": "28", "fight_time": "Sun 04/12 at 05:51 PM"}, {"name": "Suleyman Samet G\u00f6ktopal", "team": "Unity Jiu-jitsu", "division": "Master 2 Male BROWN Middle", "category_id": "2815287", "mat": "5", "fight_num": "28", "fight_time": "Sun 04/12 at 05:51 PM"}, {"name": "Brian C Aparicio", "team": "Serra BJJ", "division": "Master 2 Male BROWN Medium Heavy", "category_id": "2815291", "mat": "9", "fight_num": "29", "fight_time": "Sun 04/12 at 05:43 PM"}, {"name": "Tsetsee Batbayar", "team": "Fifty/50", "division": "Master 2 Male BROWN Medium Heavy", "category_id": "2815291", "mat": "9", "fight_num": "29", "fight_time": "Sun 04/12 at 05:43 PM"}, {"name": "Anthony Michael Craparo", "team": "Crazy 88", "division": "Master 2 Male BLACK Feather", "category_id": "2815280", "mat": "8", "fight_num": "7", "fight_time": "Sun 04/12 at 02:53 PM"}, {"name": "Zachary Green", "team": "USA Onyx Combat Sports", "division": "Master 2 Male BLACK Feather", "category_id": "2815280", "mat": "8", "fight_num": "7", "fight_time": "Sun 04/12 at 02:53 PM"}, {"name": "Jason Eugene Hamilton", "team": "Campe\u00e3o United Jiu-Jitsu", "division": "Master 2 Male BLACK Feather", "category_id": "2815280", "mat": "8", "fight_num": "5", "fight_time": "Sun 04/12 at 02:20 PM"}, {"name": "Volodymyr Boryshkevych", "team": "Masterskya", "division": "Master 2 Male BLACK Middle", "category_id": "2815288", "mat": "9", "fight_num": "14", "fight_time": "Sun 04/12 at 04:04 PM"}, {"name": "Adam Thomas Harper", "team": "SBG International (SBGI)", "division": "Master 2 Male BLACK Middle", "category_id": "2815288", "mat": "9", "fight_num": "14", "fight_time": "Sun 04/12 at 04:04 PM"}, {"name": "Daniel William Katz", "team": "SAS Team BJJ", "division": "Master 2 Male BLACK Middle", "category_id": "2815288", "mat": "9", "fight_num": "6", "fight_time": "Sun 04/12 at 03:25 PM"}, {"name": "Eldar Rafigaev", "team": "Jungle BJJ", "division": "Master 2 Male BLACK Ultra Heavy", "category_id": "2815304", "mat": "", "fight_num": "", "fight_time": ""}, {"name": "Eldar Rafigaev", "team": "Jungle BJJ", "division": "Master 2 Male BLACK Open Class", "category_id": "2815714", "mat": "2", "fight_num": "28", "fight_time": "Sun 04/12 at 05:31 PM"}, {"name": "Volodymyr Boryshkevych", "team": "Masterskya", "division": "Master 2 Male BLACK Open Class", "category_id": "2815714", "mat": "2", "fight_num": "28", "fight_time": "Sun 04/12 at 05:31 PM"}, {"name": "Zachary Green", "team": "USA Onyx Combat Sports", "division": "Master 2 Male BLACK Open Class", "category_id": "2815714", "mat": "2", "fight_num": "30", "fight_time": "Sun 04/12 at 05:45 PM"}, {"name": "Adam Thomas Harper", "team": "SBG International (SBGI)", "division": "Master 2 Male BLACK Open Class", "category_id": "2815714", "mat": "2", "fight_num": "30", "fight_time": "Sun 04/12 at 05:45 PM"}, {"name": "Luis Alberto Sepulveda", "team": "Renzo Gracie", "division": "Master 3 Male BLUE Middle", "category_id": "2815353", "mat": "6", "fight_num": "25", "fight_time": "Sun 04/12 at 05:13 PM"}, {"name": "Charles Patrick Leonard", "team": "Masterskya", "division": "Master 3 Male BLUE Middle", "category_id": "2815353", "mat": "6", "fight_num": "25", "fight_time": "Sun 04/12 at 05:13 PM"}, {"name": "Jeffrey Joseph Presta", "team": "Action & Reaction MMA Toronto", "division": "Master 3 Male BLUE Middle", "category_id": "2815353", "mat": "6", "fight_num": "26", "fight_time": "Sun 04/12 at 05:20 PM"}, {"name": "Charles Dawe", "team": "Malverne Monarch Jiu-Jitsu", "division": "Master 3 Male BLUE Medium Heavy", "category_id": "2815357", "mat": "8", "fight_num": "29", "fight_time": "Sun 04/12 at 05:10 PM"}, {"name": "Richard T. Armata II", "team": "Serra BJJ", "division": "Master 3 Male BLUE Medium Heavy", "category_id": "2815357", "mat": "8", "fight_num": "29", "fight_time": "Sun 04/12 at 05:10 PM"}, {"name": "Casey A. Newcomer", "team": "Balance", "division": "Master 3 Male BLUE Medium Heavy", "category_id": "2815357", "mat": "8", "fight_num": "27", "fight_time": "Sun 04/12 at 05:04 PM"}, {"name": "Cesar Enrique Vargas Espinoza", "team": "Renzo Gracie", "division": "Master 3 Male BLUE Heavy", "category_id": "2815361", "mat": "7", "fight_num": "24", "fight_time": "Sun 04/12 at 05:02 PM"}, {"name": "Johnattan Isaac Harton de Leon", "team": "SAS Team Syracuse", "division": "Master 3 Male BLUE Heavy", "category_id": "2815361", "mat": "7", "fight_num": "24", "fight_time": "Sun 04/12 at 05:02 PM"}, {"name": "Carlos Eugenio Ramirez", "team": "Carlos Rosado - Jiu Jitsu Modern", "division": "Master 3 Male PURPLE Middle", "category_id": "2815354", "mat": "8", "fight_num": "24", "fight_time": "Sun 04/12 at 04:51 PM"}, {"name": "Jason P. Burlingame", "team": "Renzo Gracie", "division": "Master 3 Male PURPLE Middle", "category_id": "2815354", "mat": "8", "fight_num": "24", "fight_time": "Sun 04/12 at 04:51 PM"}, {"name": "Thomas Amato", "team": "Renzo Gracie", "division": "Master 3 Male PURPLE Middle", "category_id": "2815354", "mat": "8", "fight_num": "30", "fight_time": "Sun 04/12 at 05:17 PM"}, {"name": "Hyek Cheon", "team": "A-Force Brazilian Jiu-Jitsu", "division": "Master 3 Male PURPLE Middle", "category_id": "2815354", "mat": "8", "fight_num": "30", "fight_time": "Sun 04/12 at 05:17 PM"}, {"name": "Adrian E. Giwa", "team": "Rolles Gracie Academy", "division": "Master 3 Male PURPLE Middle", "category_id": "2815354", "mat": "8", "fight_num": "31", "fight_time": "Sun 04/12 at 05:24 PM"}, {"name": "Cosme Da Silva Lima", "team": "Nova Uni\u00e3o", "division": "Master 3 Male PURPLE Middle", "category_id": "2815354", "mat": "8", "fight_num": "32", "fight_time": "Sun 04/12 at 05:31 PM"}, {"name": "Eduardo Coelho S. Pereira", "team": "Nova Uni\u00e3o", "division": "Master 3 Male PURPLE Medium Heavy", "category_id": "2815358", "mat": "7", "fight_num": "26", "fight_time": "Sun 04/12 at 05:16 PM"}, {"name": "Duy Quang Nguyen", "team": "Carlos Rosado - Jiu Jitsu Modern", "division": "Master 3 Male PURPLE Medium Heavy", "category_id": "2815358", "mat": "7", "fight_num": "26", "fight_time": "Sun 04/12 at 05:16 PM"}, {"name": "Francesco DeLucia", "team": "Notorious Mixed Martial Arts", "division": "Master 3 Male PURPLE Medium Heavy", "category_id": "2815358", "mat": "7", "fight_num": "27", "fight_time": "Sun 04/12 at 05:23 PM"}, {"name": "John Lee Koven", "team": "Alliance", "division": "Master 3 Male PURPLE Medium Heavy", "category_id": "2815358", "mat": "7", "fight_num": "27", "fight_time": "Sun 04/12 at 05:23 PM"}, {"name": "Phil Simon Goldenberg", "team": "Masterskya", "division": "Master 3 Male BROWN Middle", "category_id": "2815355", "mat": "7", "fight_num": "29", "fight_time": "Sun 04/12 at 05:37 PM"}, {"name": "Vernon C. Alcoser Jr", "team": "Renzo Gracie", "division": "Master 3 Male BROWN Middle", "category_id": "2815355", "mat": "7", "fight_num": "29", "fight_time": "Sun 04/12 at 05:37 PM"}, {"name": "Jorge Valencia", "team": "Nova Uni\u00e3o", "division": "Master 3 Male BROWN Middle", "category_id": "2815355", "mat": "7", "fight_num": "31", "fight_time": "Sun 04/12 at 05:51 PM"}, {"name": "Diego Kalaw Cuenca", "team": "Bronx Martial Arts Academy", "division": "Master 3 Male BROWN Middle", "category_id": "2815355", "mat": "7", "fight_num": "31", "fight_time": "Sun 04/12 at 05:51 PM"}, {"name": "Matthew Charles Montleon", "team": "Double Five Highland Village", "division": "Master 3 Male BROWN Middle", "category_id": "2815355", "mat": "7", "fight_num": "32", "fight_time": "Sun 04/12 at 05:58 PM"}, {"name": "Carl M. Caba\u00f1as", "team": "Bodega Jiu-Jitsu", "division": "Master 3 Male BROWN Middle", "category_id": "2815355", "mat": "7", "fight_num": "33", "fight_time": "Sun 04/12 at 06:05 PM"}, {"name": "Matthew J. Hankin", "team": "Alliance", "division": "Master 3 Male BROWN Medium Heavy", "category_id": "2815359", "mat": "8", "fight_num": "26", "fight_time": "Sun 04/12 at 05:04 PM"}, {"name": "Luc Kareem Mathieu", "team": "Nova Uni\u00e3o", "division": "Master 3 Male BROWN Medium Heavy", "category_id": "2815359", "mat": "8", "fight_num": "26", "fight_time": "Sun 04/12 at 05:04 PM"}, {"name": "Christopher Dennis Kerbis", "team": "Unity Jiu-jitsu", "division": "Master 3 Male BLACK Light", "category_id": "2815352", "mat": "8", "fight_num": "15", "fight_time": "Sun 04/12 at 03:43 PM"}, {"name": "Bernardo Correa da Cruz", "team": "Renzo Gracie", "division": "Master 3 Male BLACK Light", "category_id": "2815352", "mat": "8", "fight_num": "15", "fight_time": "Sun 04/12 at 03:43 PM"}, {"name": "Erik J Johnson", "team": "New England United", "division": "Master 3 Male BLACK Light", "category_id": "2815352", "mat": "8", "fight_num": "11", "fight_time": "Sun 04/12 at 03:17 PM"}, {"name": "Benjamin Bradley Phillips", "team": "Round Table BJJ", "division": "Master 3 Male BLACK Light", "category_id": "2815352", "mat": "8", "fight_num": "13", "fight_time": "Sun 04/12 at 03:28 PM"}, {"name": "Leon Davis Jr.", "team": "American Top Team Atlanta", "division": "Master 3 Male BLACK Medium Heavy", "category_id": "2815360", "mat": "", "fight_num": "", "fight_time": ""}, {"name": "Jarbem Ferreira Pacheco", "team": "Jiu Livre", "division": "Master 3 Male BLACK Heavy", "category_id": "2815364", "mat": "9", "fight_num": "13", "fight_time": "Sun 04/12 at 03:58 PM"}, {"name": "Casey T Lorenz", "team": "Black Hole Jiu-Jitsu", "division": "Master 3 Male BLACK Heavy", "category_id": "2815364", "mat": "9", "fight_num": "13", "fight_time": "Sun 04/12 at 03:58 PM"}, {"name": "Otavio B De Assis Jr", "team": "Gracie Barra", "division": "Master 3 Male BLACK Heavy", "category_id": "2815364", "mat": "9", "fight_num": "10", "fight_time": "Sun 04/12 at 03:47 PM"}, {"name": "Rodrigo Alexandre Fujita", "team": "Ryan Gracie Team", "division": "Master 3 Male BLACK Super Heavy", "category_id": "2815368", "mat": "8", "fight_num": "25", "fight_time": "Sun 04/12 at 04:57 PM"}, {"name": "Michael A. Petruzzi", "team": "TRA Jiu-Jitsu", "division": "Master 3 Male BLACK Super Heavy", "category_id": "2815368", "mat": "8", "fight_num": "25", "fight_time": "Sun 04/12 at 04:57 PM"}, {"name": "Luke Joel Bayas", "team": "Gianeis - The Lab Oteri BJJ", "division": "Master 3 Male BLACK Super Heavy", "category_id": "2815368", "mat": "8", "fight_num": "19", "fight_time": "Sun 04/12 at 04:22 PM"}, {"name": "Dominic John Pullano", "team": "Ares BJJ", "division": "Master 3 Male BLACK Ultra Heavy", "category_id": "2815372", "mat": "9", "fight_num": "8", "fight_time": "Sun 04/12 at 03:43 PM"}, {"name": "Jason McDowell", "team": "Action & Reaction MMA Toronto", "division": "Master 3 Male BLACK Ultra Heavy", "category_id": "2815372", "mat": "9", "fight_num": "8", "fight_time": "Sun 04/12 at 03:43 PM"}, {"name": "Lloyd Edward Clark", "team": "Crazy 88", "division": "Master 4 Male BLUE Light", "category_id": "2815417", "mat": "1", "fight_num": "22", "fight_time": "Sun 04/12 at 05:05 PM"}, {"name": "David Leitman", "team": "Pillar Jiu-Jitsu", "division": "Master 4 Male BLUE Light", "category_id": "2815417", "mat": "1", "fight_num": "22", "fight_time": "Sun 04/12 at 05:05 PM"}, {"name": "Samuel James J. Jones", "team": "TAC Team BJJ", "division": "Master 4 Male BLUE Heavy", "category_id": "2815429", "mat": "2", "fight_num": "20", "fight_time": "Sun 04/12 at 04:43 PM"}, {"name": "Alexander L. Kallmann", "team": "Clockwork Jiu-Jitsu", "division": "Master 4 Male BLUE Heavy", "category_id": "2815429", "mat": "2", "fight_num": "20", "fight_time": "Sun 04/12 at 04:43 PM"}, {"name": "Vinicius Tomich Demagalh\u00e3es", "team": "ADJJ", "division": "Master 4 Male BLUE Ultra Heavy", "category_id": "2815437", "mat": "", "fight_num": "", "fight_time": ""}, {"name": "Hendrik Sebastian Gores", "team": "Essential Jiu-Jitsu", "division": "Master 4 Male PURPLE Middle", "category_id": "2815422", "mat": "1", "fight_num": "25", "fight_time": "Sun 04/12 at 05:19 PM"}, {"name": "Jorge G. Velasquez Olvera", "team": "Team Predador Jiu-Jitsu", "division": "Master 4 Male PURPLE Middle", "category_id": "2815422", "mat": "1", "fight_num": "25", "fight_time": "Sun 04/12 at 05:19 PM"}, {"name": "Jose Villanueva", "team": "Essential Jiu-Jitsu", "division": "Master 4 Male PURPLE Middle", "category_id": "2815422", "mat": "1", "fight_num": "26", "fight_time": "Sun 04/12 at 05:26 PM"}, {"name": "Rod Martin Garcia", "team": "Unity Jiu-jitsu", "division": "Master 4 Male PURPLE Middle", "category_id": "2815422", "mat": "1", "fight_num": "26", "fight_time": "Sun 04/12 at 05:26 PM"}, {"name": "Joseph Gabriel Ziebell", "team": "Double Five Highland Village", "division": "Master 4 Male PURPLE Heavy", "category_id": "2815430", "mat": "9", "fight_num": "28", "fight_time": "Sun 04/12 at 05:36 PM"}, {"name": "Roger Lu Phillips", "team": "Native Brazilian Jiu-Jitsu", "division": "Master 4 Male PURPLE Heavy", "category_id": "2815430", "mat": "9", "fight_num": "28", "fight_time": "Sun 04/12 at 05:36 PM"}, {"name": "Ruben Belliard", "team": "Renzo Gracie", "division": "Master 4 Male BROWN Super Heavy", "category_id": "2815435", "mat": "", "fight_num": "", "fight_time": ""}, {"name": "Adam J. Duthie", "team": "Dan Covel Jiu-Jitsu", "division": "Master 4 Male BLACK Feather", "category_id": "2815416", "mat": "9", "fight_num": "18", "fight_time": "Sun 04/12 at 04:35 PM"}, {"name": "Thomas Matthew Wortman", "team": "AOJ", "division": "Master 4 Male BLACK Feather", "category_id": "2815416", "mat": "9", "fight_num": "18", "fight_time": "Sun 04/12 at 04:35 PM"}, {"name": "Nino Joseph Ridolfi", "team": "Serra BJJ", "division": "Master 4 Male BLACK Feather", "category_id": "2815416", "mat": "9", "fight_num": "12", "fight_time": "Sun 04/12 at 03:56 PM"}, {"name": "Jair Eduardo Silva Morselli", "team": "Morselli Jiu-Jitsu Academy", "division": "Master 4 Male BLACK Medium Heavy", "category_id": "2815428", "mat": "", "fight_num": "", "fight_time": ""}, {"name": "Yavuz Bozkurt \u00d6g\u00fct", "team": "VFL Wolfsburg e.V. BJJ", "division": "Master 4 Male BLACK Super Heavy", "category_id": "2815436", "mat": "8", "fight_num": "18", "fight_time": "Sun 04/12 at 04:11 PM"}, {"name": "Brett W Oteri", "team": "Gianeis - The Lab Oteri BJJ", "division": "Master 4 Male BLACK Super Heavy", "category_id": "2815436", "mat": "8", "fight_num": "18", "fight_time": "Sun 04/12 at 04:11 PM"}, {"name": "Jason Lee Mask", "team": "Cary Brazilian Jiu-Jitsu", "division": "Master 4 Male BLACK Super Heavy", "category_id": "2815436", "mat": "8", "fight_num": "14", "fight_time": "Sun 04/12 at 03:39 PM"}, {"name": "Mikhail Kalika", "team": "CheckMat", "division": "Master 4 Male BLACK Ultra Heavy", "category_id": "2815440", "mat": "9", "fight_num": "16", "fight_time": "Sun 04/12 at 04:15 PM"}, {"name": "Rodrigo Franco Montenegro Francisco", "team": "Breakfast Club Jiu-Jitsu", "division": "Master 4 Male BLACK Ultra Heavy", "category_id": "2815440", "mat": "9", "fight_num": "16", "fight_time": "Sun 04/12 at 04:15 PM"}, {"name": "Reuben Martinez", "team": "Gracie Barra", "division": "Master 5 Male BROWN Middle", "category_id": "2815491", "mat": "", "fight_num": "", "fight_time": ""}, {"name": "Reuben Martinez", "team": "Gracie Barra", "division": "Master 5 Male BROWN Open Class", "category_id": "2815744", "mat": "", "fight_num": "", "fight_time": ""}, {"name": "Richard Jan Byrne", "team": "Unity Jiu-jitsu", "division": "Master 6 Male BLACK Light", "category_id": "2815556", "mat": "9", "fight_num": "17", "fight_time": "Sun 04/12 at 04:22 PM"}, {"name": "John P Cambronero", "team": "Serra BJJ", "division": "Master 6 Male BLACK Light", "category_id": "2815556", "mat": "9", "fight_num": "17", "fight_time": "Sun 04/12 at 04:22 PM"}, {"name": "Juan Alberto Cosme", "team": "Pedro Sauer Team", "division": "Master 7 Male BLUE Medium Heavy", "category_id": "2815663", "mat": "6", "fight_num": "21", "fight_time": "Sun 04/12 at 04:46 PM"}, {"name": "Patrick James Iozzo", "team": "API - Ascension Athletics", "division": "Master 7 Male BLUE Medium Heavy", "category_id": "2815663", "mat": "6", "fight_num": "21", "fight_time": "Sun 04/12 at 04:46 PM"}, {"name": "Lazaro Joaquin Cosme", "team": "Pedro Sauer Team", "division": "Master 7 Male PURPLE Ultra Heavy", "category_id": "2815676", "mat": "", "fight_num": "", "fight_time": ""}]}